[
  {
    "name": "Vedant Bhansali",
    "aum": 74,
    "revenue": 0.04,
    "netMob": 1.0899999999999999,
    "m50": 2,
    "sip": 21,
    "aumTarget": 116,
    "revTarget": 1.6,
    "ledgerTotal": 1.0899999999999999,
    "journey": [
      {
        "label": "AUM",
        "target": 116,
        "monthlyRunRate": 3.5,
        "actual": 74,
        "newRunRate": 3.8181818181818183
      },
      {
        "label": "Revenue",
        "target": 1.6,
        "monthlyRunRate": 0.13333333333333333,
        "actual": 0.04,
        "newRunRate": 0.14181818181818182
      },
      {
        "label": "Net Mob",
        "target": 27,
        "monthlyRunRate": 2.25,
        "actual": 1.0899999999999999,
        "newRunRate": 2.3554545454545455
      },
      {
        "label": "Mission 50",
        "target": 12,
        "monthlyRunRate": 1,
        "actual": 2,
        "newRunRate": 0.9090909090909091
      },
      {
        "label": "SIP Book",
        "target": 36,
        "monthlyRunRate": 3,
        "actual": 21,
        "newRunRate": 1.3636363636363635
      }
    ],
    "activity": [
      {
        "param": "Client Meetings",
        "target": 44,
        "actual": 20,
        "gap": 24
      },
      {
        "param": "Product Meetings",
        "target": 10,
        "actual": 4,
        "gap": 6
      },
      {
        "param": "WILLs",
        "target": 1,
        "actual": 0,
        "gap": 1
      },
      {
        "param": "DE Audit",
        "target": 1,
        "actual": 0,
        "gap": 1
      },
      {
        "param": "MF Audit",
        "target": 1,
        "actual": 0,
        "gap": 1
      },
      {
        "param": "PMS Audit",
        "target": 1,
        "actual": 1,
        "gap": 0
      },
      {
        "param": "Insurance Audit",
        "target": 1,
        "actual": 1,
        "gap": 0
      },
      {
        "param": "TNC Calculator",
        "target": 1,
        "actual": 0,
        "gap": 1
      },
      {
        "param": "Leverage",
        "target": 1,
        "actual": 0,
        "gap": 1
      },
      {
        "param": "SIP",
        "target": 0,
        "actual": 1,
        "gap": -1
      },
      {
        "param": "M50",
        "target": 1,
        "actual": 2,
        "gap": -1
      }
    ],
    "leverage": [
      {
        "label": "Leverage Done till FY26",
        "value": 1.8
      },
      {
        "label": "New Leverage Done",
        "value": 0
      },
      {
        "label": "Total Leverage Done",
        "value": 1.8
      },
      {
        "label": "% of Total AUM",
        "value": 0.15
      }
    ],
    "plan": [
      {
        "client": "Kothari",
        "asset": "MF",
        "expectedAmt": 1,
        "expectedRedemption": 0,
        "netPlan": 1,
        "prob": 1
      },
      {
        "client": "Kothari",
        "asset": "SP",
        "expectedAmt": 1.1,
        "expectedRedemption": 0,
        "netPlan": 1.1,
        "prob": 50
      },
      {
        "client": "Nensey",
        "asset": "SP",
        "expectedAmt": 1.1,
        "expectedRedemption": 0,
        "netPlan": 1.1,
        "prob": 80
      },
      {
        "client": "Wala",
        "asset": "MF",
        "expectedAmt": 0.25,
        "expectedRedemption": 0,
        "netPlan": 0.25,
        "prob": 20
      },
      {
        "client": "Murali",
        "asset": "MF",
        "expectedAmt": 1,
        "expectedRedemption": 0,
        "netPlan": 1,
        "prob": 100
      }
    ],
    "planTotalAmt": 4.45,
    "planTotalRedemption": 0,
    "planNetTotal": 4.45,
    "planWeighted": 2.49,
    "ledger": [
      {
        "client": "Murali",
        "asset": "MF",
        "month": "April",
        "purchase": 1,
        "redemption": 0,
        "net": 1
      },
      {
        "client": "Fatnani",
        "asset": "MF",
        "month": "April",
        "purchase": 0,
        "redemption": 0.15,
        "net": -0.15
      },
      {
        "client": "Markmart",
        "asset": "MF",
        "month": "April",
        "purchase": 0.1,
        "redemption": 0,
        "net": 0.1
      },
      {
        "client": "Pramod Agarwal",
        "asset": "MF",
        "month": "April",
        "purchase": 0.14,
        "redemption": 0,
        "net": 0.14
      }
    ],
    "lastUpdated": "2026-05-01T04:40:53.756Z"
  },
  {
    "name": "Piyush Dungarpuria",
    "aum": 0,
    "revenue": 0,
    "netMob": 0,
    "m50": 0,
    "sip": 0,
    "aumTarget": 0,
    "revTarget": 0,
    "ledgerTotal": 0,
    "journey": [
      {
        "label": "AUM",
        "target": 0,
        "monthlyRunRate": 0,
        "actual": 0,
        "newRunRate": 0
      },
      {
        "label": "Revenue",
        "target": 0,
        "monthlyRunRate": 0,
        "actual": 0,
        "newRunRate": 0
      },
      {
        "label": "Net Mob",
        "target": 0,
        "monthlyRunRate": 0,
        "actual": 0,
        "newRunRate": 0
      },
      {
        "label": "Mission 50",
        "target": 0,
        "monthlyRunRate": 0,
        "actual": 0,
        "newRunRate": 0
      },
      {
        "label": "SIP Book",
        "target": 0,
        "monthlyRunRate": 0,
        "actual": 0,
        "newRunRate": 0
      }
    ],
    "activity": [
      {
        "param": "Client Meetings",
        "target": 0,
        "actual": 0,
        "gap": 0
      },
      {
        "param": "Product Meetings",
        "target": 0,
        "actual": 0,
        "gap": 0
      },
      {
        "param": "WILLs",
        "target": 0,
        "actual": 0,
        "gap": 0
      },
      {
        "param": "DE Audit",
        "target": 0,
        "actual": 0,
        "gap": 0
      },
      {
        "param": "MF Audit",
        "target": 0,
        "actual": 0,
        "gap": 0
      },
      {
        "param": "PMS Audit",
        "target": 0,
        "actual": 0,
        "gap": 0
      },
      {
        "param": "Insurance Audit",
        "target": 0,
        "actual": 0,
        "gap": 0
      },
      {
        "param": "TNC Calculator",
        "target": 0,
        "actual": 0,
        "gap": 0
      },
      {
        "param": "Leverage",
        "target": 0,
        "actual": 0,
        "gap": 0
      },
      {
        "param": "SIP",
        "target": 0,
        "actual": 0,
        "gap": 0
      },
      {
        "param": "M50",
        "target": 0,
        "actual": 0,
        "gap": 0
      }
    ],
    "leverage": [
      {
        "label": "Leverage Done till FY26",
        "value": 0
      },
      {
        "label": "New Leverage Done",
        "value": 0
      },
      {
        "label": "Total Leverage Done",
        "value": 0
      },
      {
        "label": "% of Total AUM",
        "value": "#DIV/0!"
      }
    ],
    "plan": [],
    "planTotalAmt": 0,
    "planTotalRedemption": 0,
    "planNetTotal": 0,
    "planWeighted": 0,
    "ledger": [],
    "lastUpdated": "2026-05-01T04:40:53.914Z"
  },
  {
    "name": "Majid Shaikh",
    "aum": 270.59,
    "revenue": 0.49,
    "netMob": 0.30977549999999976,
    "m50": 0,
    "sip": 35.98,
    "aumTarget": 389.42023034286,
    "revTarget": 4.1914544125,
    "ledgerTotal": 0.30977549999999976,
    "journey": [
      {
        "label": "AUM",
        "target": 389.42023034286,
        "monthlyRunRate": 9.902619161866753,
        "actual": 270.59,
        "newRunRate": 10.802748212987275
      },
      {
        "label": "Revenue",
        "target": 4.1914544125,
        "monthlyRunRate": 0.3492878677083333,
        "actual": 0.49,
        "newRunRate": 0.3364958556818181
      },
      {
        "label": "Net Mob",
        "target": 64.27,
        "monthlyRunRate": 5.355833333333333,
        "actual": 0.30977549999999976,
        "newRunRate": 5.814565863636363
      },
      {
        "label": "Mission 50",
        "target": 34,
        "monthlyRunRate": 2.8333333333333335,
        "actual": 0,
        "newRunRate": 3.090909090909091
      },
      {
        "label": "SIP Book",
        "target": 46.61,
        "monthlyRunRate": 3.8841666666666668,
        "actual": 35.98,
        "newRunRate": 0.9663636363636366
      }
    ],
    "activity": [
      {
        "param": "Client Meetings",
        "target": 20,
        "actual": 20,
        "gap": 0
      },
      {
        "param": "Product Meetings",
        "target": 10,
        "actual": 10,
        "gap": 0
      },
      {
        "param": "WILLs",
        "target": 1,
        "actual": 0,
        "gap": 1
      },
      {
        "param": "DE Audit",
        "target": 1,
        "actual": 1,
        "gap": 0
      },
      {
        "param": "MF Audit",
        "target": 2,
        "actual": 1,
        "gap": 1
      },
      {
        "param": "PMS Audit",
        "target": 0,
        "actual": 0,
        "gap": 0
      },
      {
        "param": "Insurance Audit",
        "target": 0,
        "actual": 0,
        "gap": 0
      },
      {
        "param": "TNC Calculator",
        "target": 1,
        "actual": 0,
        "gap": 1
      },
      {
        "param": "Leverage",
        "target": 1.1,
        "actual": 0,
        "gap": 1.1
      },
      {
        "param": "SIP",
        "target": 4,
        "actual": 0,
        "gap": 4
      },
      {
        "param": "M50",
        "target": 1,
        "actual": 0,
        "gap": 1
      }
    ],
    "leverage": [
      {
        "label": "Leverage Done till FY26",
        "value": 31
      },
      {
        "label": "New Leverage Done",
        "value": 0
      },
      {
        "label": "Total Leverage Done",
        "value": 31
      },
      {
        "label": "% of Total AUM",
        "value": 0.15816326530612246
      }
    ],
    "plan": [
      {
        "client": "K T Jithendran",
        "asset": "NSP",
        "expectedAmt": 2,
        "expectedRedemption": 0,
        "netPlan": 2,
        "prob": 80
      },
      {
        "client": "Jayant Shripad Jambotkar",
        "asset": "NSP",
        "expectedAmt": 1.1,
        "expectedRedemption": 0,
        "netPlan": 1.1,
        "prob": 80
      },
      {
        "client": "Chetan Shah",
        "asset": "Leverage",
        "expectedAmt": 1.1,
        "expectedRedemption": 0,
        "netPlan": 1.1,
        "prob": 80
      },
      {
        "client": "Adyasha Rath",
        "asset": "NSP",
        "expectedAmt": 1.1,
        "expectedRedemption": 0,
        "netPlan": 1.1,
        "prob": 80
      },
      {
        "client": "Vijay Mayekar",
        "asset": "EMF",
        "expectedAmt": 1,
        "expectedRedemption": 0,
        "netPlan": 1,
        "prob": 80
      },
      {
        "client": "Pranay Shetty",
        "asset": "EMF",
        "expectedAmt": 1,
        "expectedRedemption": 0,
        "netPlan": 1,
        "prob": 80
      }
    ],
    "planTotalAmt": 7.300000000000001,
    "planTotalRedemption": 0,
    "planNetTotal": 7.300000000000001,
    "planWeighted": 5.84,
    "ledger": [
      {
        "client": "Adithya Janardhan Bhat",
        "asset": "EMF",
        "month": "April",
        "purchase": 0.029998,
        "redemption": 0,
        "net": 0.029998
      },
      {
        "client": "Ajay Kurhekar",
        "asset": "EMF",
        "month": "April",
        "purchase": 0.000998,
        "redemption": 0,
        "net": 0.000998
      },
      {
        "client": "Adyasha Rath",
        "asset": "EMF",
        "month": "April",
        "purchase": 0,
        "redemption": 0.74652,
        "net": -0.74652
      },
      {
        "client": "Adyasha Rath",
        "asset": "NSP",
        "month": "April",
        "purchase": 1.1,
        "redemption": 0,
        "net": 1.1
      },
      {
        "client": "Ashok Chandrashekhar Vaidya",
        "asset": "NSP",
        "month": "April",
        "purchase": 0,
        "redemption": 0.42067,
        "net": -0.42067
      },
      {
        "client": "Bhaskar Subramanian",
        "asset": "EMF",
        "month": "April",
        "purchase": 0,
        "redemption": 0.045301,
        "net": -0.045301
      },
      {
        "client": "Gaurav Jain",
        "asset": "EMF",
        "month": "April",
        "purchase": 0.099995,
        "redemption": 0,
        "net": 0.099995
      },
      {
        "client": "Hrishikesh Dinkar Samant",
        "asset": "EMF",
        "month": "April",
        "purchase": 0.009998,
        "redemption": 0,
        "net": 0.009998
      },
      {
        "client": "Imran Azizur Rehman Siddiqui",
        "asset": "EMF",
        "month": "April",
        "purchase": 0,
        "redemption": 0.00009,
        "net": -0.00009
      },
      {
        "client": "Jayant Shripad Jambotkar",
        "asset": "EMF",
        "month": "April",
        "purchase": 0.502626,
        "redemption": 0.502655,
        "net": -0.000028999999999945736
      },
      {
        "client": "Karat Tazhtetil Jithendran",
        "asset": "EMF",
        "month": "April",
        "purchase": 0.331949,
        "redemption": 1.185653,
        "net": -0.853704
      },
      {
        "client": "Karat Tazhtetil Jithendran",
        "asset": "NSP",
        "month": "April",
        "purchase": 2,
        "redemption": 1.88488,
        "net": 0.11511999999999989
      },
      {
        "client": "Karat Tazhtetil Jithendran",
        "asset": "Shares",
        "month": "April",
        "purchase": 1.986875,
        "redemption": 2.0067575,
        "net": -0.019882500000000025
      },
      {
        "client": "Milind S Korde",
        "asset": "EMF",
        "month": "April",
        "purchase": 0.039986,
        "redemption": 0,
        "net": 0.039986
      },
      {
        "client": "Nimit S Chavan",
        "asset": "EMF",
        "month": "April",
        "purchase": 0.000099,
        "redemption": 0,
        "net": 0.000099
      },
      {
        "client": "Paras Ram Vishwakarma",
        "asset": "EMF",
        "month": "April",
        "purchase": 0.019998,
        "redemption": 0,
        "net": 0.019998
      },
      {
        "client": "Purushothaman KG",
        "asset": "EMF",
        "month": "April",
        "purchase": 0.37401,
        "redemption": 0.368419,
        "net": 0.005591000000000013
      },
      {
        "client": "Ravindra N Katre",
        "asset": "EMF",
        "month": "April",
        "purchase": 0,
        "redemption": 0.724622,
        "net": -0.724622
      },
      {
        "client": "Ravindra N Katre",
        "asset": "NSP",
        "month": "April",
        "purchase": 1.4625,
        "redemption": 0,
        "net": 1.4625
      },
      {
        "client": "Rajesh J Doshi",
        "asset": "EMF",
        "month": "April",
        "purchase": 0.683947,
        "redemption": 0.582963,
        "net": 0.10098399999999996
      },
      {
        "client": "Shivkumar Ananthakrishnan",
        "asset": "EMF",
        "month": "April",
        "purchase": 0.045469,
        "redemption": 0.085194,
        "net": -0.039725
      },
      {
        "client": "Sumit Mohan Nadgir",
        "asset": "EMF",
        "month": "April",
        "purchase": 0.377903,
        "redemption": 0.105423,
        "net": 0.27248
      },
      {
        "client": "Shoaib Fakhruddin Padaria",
        "asset": "EMF",
        "month": "April",
        "purchase": 0.144297,
        "redemption": 0.162608,
        "net": -0.018310999999999994
      },
      {
        "client": "Sunita Anil Gajwani",
        "asset": "EMF",
        "month": "April",
        "purchase": 0.019998,
        "redemption": 0,
        "net": 0.019998
      },
      {
        "client": "Yukta Kondiba Sakpal",
        "asset": "EMF",
        "month": "April",
        "purchase": 0.000099,
        "redemption": 0,
        "net": 0.000099
      },
      {
        "client": "Deepak Dhar",
        "asset": "EMF",
        "month": "April",
        "purchase": 0,
        "redemption": 0.099214,
        "net": -0.099214
      }
    ],
    "lastUpdated": "2026-05-01T04:40:54.087Z"
  },
  {
    "name": "Karan Desai",
    "aum": 182,
    "revenue": 0.29,
    "netMob": 4.859999999999999,
    "m50": 0,
    "sip": 0,
    "aumTarget": 234,
    "revTarget": 3,
    "ledgerTotal": 4.859999999999999,
    "journey": [
      {
        "label": "AUM",
        "target": 234,
        "monthlyRunRate": 4.333333333333333,
        "actual": 182,
        "newRunRate": 4.7272727272727275
      },
      {
        "label": "Revenue",
        "target": 3,
        "monthlyRunRate": 0.25,
        "actual": 0.29,
        "newRunRate": 0.24636363636363637
      },
      {
        "label": "Net Mob",
        "target": 40,
        "monthlyRunRate": 3.3333333333333335,
        "actual": 4.859999999999999,
        "newRunRate": 3.194545454545455
      },
      {
        "label": "Mission 50",
        "target": 10,
        "monthlyRunRate": 0.8333333333333334,
        "actual": 0,
        "newRunRate": 0.9090909090909091
      },
      {
        "label": "SIP Book",
        "target": 15,
        "monthlyRunRate": 1.25,
        "actual": 0,
        "newRunRate": 1.3636363636363635
      }
    ],
    "activity": [
      {
        "param": "Client Meetings",
        "target": 33,
        "actual": 25,
        "gap": 8
      },
      {
        "param": "Product Meetings",
        "target": 12,
        "actual": 12,
        "gap": 0
      },
      {
        "param": "WILLs",
        "target": 1,
        "actual": 0,
        "gap": 1
      },
      {
        "param": "DE Audit",
        "target": 1,
        "actual": 0,
        "gap": 1
      },
      {
        "param": "MF Audit",
        "target": 2,
        "actual": 2,
        "gap": 0
      },
      {
        "param": "PMS Audit",
        "target": 0,
        "actual": 0,
        "gap": 0
      },
      {
        "param": "Insurance Audit",
        "target": 0,
        "actual": 0,
        "gap": 0
      },
      {
        "param": "TNC Calculator",
        "target": 2,
        "actual": 0,
        "gap": 2
      },
      {
        "param": "Leverage",
        "target": 0,
        "actual": 0,
        "gap": 0
      },
      {
        "param": "SIP",
        "target": 1,
        "actual": 1,
        "gap": 0
      },
      {
        "param": "M50",
        "target": 1,
        "actual": 0,
        "gap": 1
      }
    ],
    "leverage": [
      {
        "label": "Leverage Done till FY26",
        "value": 1.5
      },
      {
        "label": "New Leverage Done",
        "value": 0
      },
      {
        "label": "Total Leverage Done",
        "value": 1.5
      },
      {
        "label": "% of Qualified AUM",
        "value": 0.125
      }
    ],
    "plan": [
      {
        "client": "Hemen Vimadalal",
        "asset": "MF",
        "expectedAmt": 0.95,
        "expectedRedemption": 0,
        "netPlan": 0.95,
        "prob": 80
      },
      {
        "client": "Sharad Gupta",
        "asset": "SP",
        "expectedAmt": 1.1,
        "expectedRedemption": 0,
        "netPlan": 1.1,
        "prob": 80
      },
      {
        "client": "Gautam Bavishi",
        "asset": "MF",
        "expectedAmt": 0.25,
        "expectedRedemption": 0,
        "netPlan": 0.25,
        "prob": 80
      }
    ],
    "planTotalAmt": 2.3,
    "planTotalRedemption": 0,
    "planNetTotal": 2.3,
    "planWeighted": 1.84,
    "ledger": [
      {
        "client": "Hemen Vimadalal",
        "asset": "MF",
        "month": "April",
        "purchase": 1.63,
        "redemption": 0,
        "net": 1.63
      },
      {
        "client": "Deepak Patkar",
        "asset": "MF",
        "month": "April",
        "purchase": 0.1,
        "redemption": 0,
        "net": 0.1
      },
      {
        "client": "Navneet Bansal",
        "asset": "MF",
        "month": "April",
        "purchase": 0.2,
        "redemption": 0,
        "net": 0.2
      },
      {
        "client": "Gautam Bavishi",
        "asset": "MF",
        "month": "April",
        "purchase": 0.25,
        "redemption": 0,
        "net": 0.25
      },
      {
        "client": "Reginald Sequeira",
        "asset": "MF",
        "month": "April",
        "purchase": 0.18,
        "redemption": 0,
        "net": 0.18
      },
      {
        "client": "Falak Ami Thanawala",
        "asset": "SP",
        "month": "April",
        "purchase": 2.5,
        "redemption": 0,
        "net": 2.5
      }
    ],
    "lastUpdated": "2026-05-01T04:40:54.252Z"
  },
  {
    "name": "Gaurav Kumar",
    "aum": 28,
    "revenue": 0.06,
    "netMob": -0.3218542999999999,
    "m50": 1,
    "sip": 0.0296,
    "aumTarget": 56.6,
    "revTarget": 0.5589999999999999,
    "ledgerTotal": -0.3218542999999999,
    "journey": [
      {
        "label": "AUM",
        "target": 56.6,
        "monthlyRunRate": 2.4283333333333332,
        "actual": 28,
        "newRunRate": 2.6
      },
      {
        "label": "Revenue",
        "target": 0.5589999999999999,
        "monthlyRunRate": 0.04658333333333333,
        "actual": 0.06,
        "newRunRate": 0.045363636363636356
      },
      {
        "label": "Net Mob",
        "target": 24.5,
        "monthlyRunRate": 2.0416666666666665,
        "actual": -0.3218542999999999,
        "newRunRate": 2.256532209090909
      },
      {
        "label": "Mission 50",
        "target": 12,
        "monthlyRunRate": 1,
        "actual": 1,
        "newRunRate": 1
      },
      {
        "label": "SIP Book",
        "target": 0.08,
        "monthlyRunRate": 0.006666666666666667,
        "actual": 0.0296,
        "newRunRate": 0.004581818181818182
      }
    ],
    "activity": [
      {
        "param": "Client Meetings",
        "target": 13,
        "actual": 5,
        "gap": 8
      },
      {
        "param": "Product Meetings",
        "target": 2,
        "actual": 1,
        "gap": 1
      },
      {
        "param": "WILLs",
        "target": 2,
        "actual": 0,
        "gap": 2
      },
      {
        "param": "DE Audit",
        "target": 1,
        "actual": 0,
        "gap": 1
      },
      {
        "param": "MF Audit",
        "target": 1,
        "actual": 0,
        "gap": 1
      },
      {
        "param": "PMS Audit",
        "target": 2,
        "actual": 0,
        "gap": 2
      },
      {
        "param": "Insurance Audit",
        "target": 0,
        "actual": 1,
        "gap": -1
      },
      {
        "param": "TNC Calculator",
        "target": 2,
        "actual": 0,
        "gap": 2
      },
      {
        "param": "Leverage",
        "target": 0,
        "actual": 0,
        "gap": 0
      },
      {
        "param": "SIP",
        "target": 0,
        "actual": 0,
        "gap": 0
      },
      {
        "param": "M50",
        "target": 1,
        "actual": 0,
        "gap": 1
      }
    ],
    "leverage": [
      {
        "label": "Leverage Done till FY26",
        "value": 0
      },
      {
        "label": "New Leverage Done",
        "value": 0
      },
      {
        "label": "Total Leverage Done",
        "value": 0
      },
      {
        "label": "% of Total AUM",
        "value": "#DIV/0!"
      }
    ],
    "plan": [
      {
        "client": "PALLAVI VISHWAS WAD",
        "asset": "NSP",
        "expectedAmt": 1.5,
        "expectedRedemption": 1.8,
        "netPlan": -0.30000000000000004,
        "prob": 50
      },
      {
        "client": "PALLAVI VISHWAS WAD",
        "asset": "Others",
        "expectedAmt": 0.3,
        "expectedRedemption": 0,
        "netPlan": 0.3,
        "prob": 50
      },
      {
        "client": "Kumar Ram Kanuga",
        "asset": "MF",
        "expectedAmt": 0.15,
        "expectedRedemption": 0,
        "netPlan": 0.15,
        "prob": 50
      },
      {
        "client": "PIYUSH DUNGARPARIA",
        "asset": "MF",
        "expectedAmt": 0.2,
        "expectedRedemption": 0,
        "netPlan": 0.2,
        "prob": 80
      },
      {
        "client": "ARUN KUMAR SRIVASTAVA",
        "asset": "MF",
        "expectedAmt": 0.25,
        "expectedRedemption": 0,
        "netPlan": 0.25,
        "prob": 40
      },
      {
        "client": "ALIASGAR H SUNASARA",
        "asset": "MF",
        "expectedAmt": 0.05,
        "expectedRedemption": 0,
        "netPlan": 0.05,
        "prob": 80
      },
      {
        "client": "BALASUBRAMANIAM VENKATESH IYER",
        "asset": "MF",
        "expectedAmt": 0.2,
        "expectedRedemption": 0,
        "netPlan": 0.2,
        "prob": 50
      },
      {
        "client": "NEELAM RAJESH GEHANI",
        "asset": "MF",
        "expectedAmt": 0.15,
        "expectedRedemption": 0,
        "netPlan": 0.15,
        "prob": 50
      }
    ],
    "planTotalAmt": 2.8,
    "planTotalRedemption": 1.8,
    "planNetTotal": 1,
    "planWeighted": 1.4500000000000002,
    "ledger": [
      {
        "client": "Harshala Anant Mankame",
        "asset": "MF",
        "month": "April",
        "purchase": 0.00249988,
        "redemption": 0,
        "net": 0.00249988
      },
      {
        "client": "Harshala Anant Mankame",
        "asset": "MF",
        "month": "April",
        "purchase": 0.00249988,
        "redemption": 0,
        "net": 0.00249988
      },
      {
        "client": "Harshala Anant Mankame",
        "asset": "MF",
        "month": "April",
        "purchase": 0.00499975,
        "redemption": 0,
        "net": 0.00499975
      },
      {
        "client": "PIYUSH DUNGARPURIYA",
        "asset": "MF",
        "month": "April",
        "purchase": 0.00249988,
        "redemption": 0,
        "net": 0.00249988
      },
      {
        "client": "ALIASGAR H SUNASARA",
        "asset": "MF",
        "month": "April",
        "purchase": 0.0099995,
        "redemption": 0,
        "net": 0.0099995
      },
      {
        "client": "ALIASGAR H SUNASARA",
        "asset": "MF",
        "month": "April",
        "purchase": 0.019999,
        "redemption": 0,
        "net": 0.019999
      },
      {
        "client": "ALIASGAR H SUNASARA",
        "asset": "MF",
        "month": "April",
        "purchase": 0.0099995,
        "redemption": 0,
        "net": 0.0099995
      },
      {
        "client": "ALIASGAR H SUNASARA",
        "asset": "MF",
        "month": "April",
        "purchase": 0.0099995,
        "redemption": 0,
        "net": 0.0099995
      },
      {
        "client": "VINITA DUNGARPURIA",
        "asset": "SP",
        "month": "April",
        "purchase": 0,
        "redemption": 0.3904509,
        "net": -0.3904509
      },
      {
        "client": "PIYUSH DUNGARPURIYA",
        "asset": "MF",
        "month": "April",
        "purchase": 0.00249988,
        "redemption": 0,
        "net": 0.00249988
      },
      {
        "client": "HARSHIL DUNGARPURIA REP BY PIYUSH DUNGARPURIA",
        "asset": "MF",
        "month": "April",
        "purchase": 0.00249988,
        "redemption": 0,
        "net": 0.00249988
      },
      {
        "client": "HARSHIL DUNGARPURIA REP BY PIYUSH DUNGARPURIA",
        "asset": "MF",
        "month": "April",
        "purchase": 0.00099995,
        "redemption": 0,
        "net": 0.00099995
      },
      {
        "client": "GAURAV KUMAR",
        "asset": "MF",
        "month": "April",
        "purchase": 0.0001,
        "redemption": 0,
        "net": 0.0001
      },
      {
        "client": "VIRENDRA NATH GUPTA",
        "asset": "SP",
        "month": "April",
        "purchase": 0,
        "redemption": 0.0406446,
        "net": -0.0406446
      },
      {
        "client": "VIRENDRA NATH GUPTA",
        "asset": "MF",
        "month": "April",
        "purchase": 0.0406446,
        "redemption": 0,
        "net": 0.0406446
      }
    ],
    "lastUpdated": "2026-05-01T04:40:54.697Z"
  },
  {
    "name": "Pawan Vyas",
    "aum": 17.6,
    "revenue": 0.01,
    "netMob": -0.245,
    "m50": 0,
    "sip": 0,
    "aumTarget": 40,
    "revTarget": 0.4,
    "ledgerTotal": -0.245,
    "journey": [
      {
        "label": "AUM",
        "target": 40,
        "monthlyRunRate": 1.8666666666666665,
        "actual": 17.6,
        "newRunRate": 2.036363636363636
      },
      {
        "label": "Revenue",
        "target": 0.4,
        "monthlyRunRate": 0.03333333333333333,
        "actual": 0.01,
        "newRunRate": 0.035454545454545454
      },
      {
        "label": "Net Mob",
        "target": 20,
        "monthlyRunRate": 1.6666666666666667,
        "actual": -0.245,
        "newRunRate": 1.8404545454545456
      },
      {
        "label": "Mission 50",
        "target": 12,
        "monthlyRunRate": 1,
        "actual": 0,
        "newRunRate": 1.0909090909090908
      },
      {
        "label": "SIP Book",
        "target": 5,
        "monthlyRunRate": 0.4166666666666667,
        "actual": 0,
        "newRunRate": 0.45454545454545453
      }
    ],
    "activity": [
      {
        "param": "Client Meetings",
        "target": 9,
        "actual": 10,
        "gap": -1
      },
      {
        "param": "Product Meetings",
        "target": 1,
        "actual": 1,
        "gap": 0
      },
      {
        "param": "WILLs",
        "target": 0,
        "actual": 0,
        "gap": 0
      },
      {
        "param": "DE Audit",
        "target": 1,
        "actual": 0,
        "gap": 1
      },
      {
        "param": "MF Audit",
        "target": 1,
        "actual": 0,
        "gap": 1
      },
      {
        "param": "PMS Audit",
        "target": 0,
        "actual": 0,
        "gap": 0
      },
      {
        "param": "Insurance Audit",
        "target": 0,
        "actual": 1,
        "gap": -1
      },
      {
        "param": "TNC Calculator",
        "target": 1,
        "actual": 1,
        "gap": 0
      },
      {
        "param": "Leverage",
        "target": 0,
        "actual": 0,
        "gap": 0
      },
      {
        "param": "SIP",
        "target": 0,
        "actual": 0,
        "gap": 0
      },
      {
        "param": "M50",
        "target": 1,
        "actual": 0,
        "gap": 1
      }
    ],
    "leverage": [
      {
        "label": "Leverage Done till FY26",
        "value": 0.75
      },
      {
        "label": "New Leverage Done",
        "value": 0
      },
      {
        "label": "Total Leverage Done",
        "value": 0.75
      },
      {
        "label": "% of Total AUM",
        "value": 0.075
      }
    ],
    "plan": [
      {
        "client": "Raorane Family",
        "asset": "MF",
        "expectedAmt": 1,
        "expectedRedemption": 0,
        "netPlan": 1,
        "prob": 80
      },
      {
        "client": "Ameeta Munshi",
        "asset": "MF",
        "expectedAmt": 0,
        "expectedRedemption": 0.1,
        "netPlan": -0.1,
        "prob": 80
      },
      {
        "client": "Sanjay Karwa",
        "asset": "MF",
        "expectedAmt": 0.2,
        "expectedRedemption": 0,
        "netPlan": 0.2,
        "prob": 80
      },
      {
        "client": "Abdul Patni",
        "asset": "SP",
        "expectedAmt": 0.25,
        "expectedRedemption": 0,
        "netPlan": 0.25,
        "prob": 80
      },
      {
        "client": "Akhilesh",
        "asset": "MF",
        "expectedAmt": 0.15,
        "expectedRedemption": 0,
        "netPlan": 0.15,
        "prob": 80
      }
    ],
    "planTotalAmt": 1.5999999999999999,
    "planTotalRedemption": 0.1,
    "planNetTotal": 1.5,
    "planWeighted": 1.2800000000000002,
    "ledger": [
      {
        "client": "Sanjay Karwa",
        "asset": "MF",
        "month": "April",
        "purchase": 0.015,
        "redemption": 0,
        "net": 0.015
      },
      {
        "client": "Ameeta Munshi",
        "asset": "MF",
        "month": "April",
        "purchase": 0,
        "redemption": 0.12,
        "net": -0.12
      },
      {
        "client": "Raorane Family",
        "asset": "MF",
        "month": "April",
        "purchase": 0.17,
        "redemption": 0,
        "net": 0.17
      },
      {
        "client": "Abdul Patni",
        "asset": "SP",
        "month": "April",
        "purchase": 0,
        "redemption": 0.31,
        "net": -0.31
      }
    ],
    "lastUpdated": "2026-05-01T04:40:54.869Z"
  }
]